thecodingsociety/__init__.py
thecodingsociety/parse.py
thecodingscoiety-0.0.3.dist-info/LICENSE
thecodingscoiety-0.0.3.dist-info/METADATA
thecodingscoiety-0.0.3.dist-info/WHEEL
thecodingscoiety-0.0.3.dist-info/top_level.txt
thecodingscoiety-0.0.3.dist-info/RECORD
