Metadata-Version: 2.1
Name: thecodingscoiety
Version: 0.0.3
Summary: A package of function created by and for The Coding Society
Author-email: The Coding Society <codingsociety@psdc.org.in>, "aviiciii (Laaveshwaran Parthiban)" <laavesh1@gmail.com>
Project-URL: Homepage, https://github.com/thecoding-society/rollno-parser
Project-URL: Bug Tracker, https://github.com/thecoding-society/rollno-parser/issues
Classifier: Programming Language :: Python :: 3
Classifier: License :: OSI Approved :: MIT License
Classifier: Operating System :: OS Independent
Requires-Python: >=3.7
License-File: LICENSE
Requires-Dist: regex (>=2022.10.31)
